<?xml version="1.0"?>
<metadata xml:lang="pt"><Esri><CreaDate>20221228</CreaDate><CreaTime>16242700</CreaTime><ArcGISFormat>1.0</ArcGISFormat><SyncOnce>TRUE</SyncOnce><ModDate>20221228</ModDate><ModTime>191005</ModTime><scaleRange><minScale>150000000</minScale><maxScale>5000</maxScale></scaleRange><ArcGISProfile>ItemDescription</ArcGISProfile></Esri><toolbox name="Modelo Base" alias=""><arcToolboxHelpPath>c:\program files (x86)\arcgis\desktop10.8\Help\gp</arcToolboxHelpPath><toolsets/></toolbox><dataIdInfo><idCitation><resTitle>Modelo Base</resTitle></idCitation><idPurp>Um modelo simples, que da a base para a construção da ferramenta</idPurp><searchKeys><keyword>Modelo Base</keyword><keyword>Python</keyword><keyword>Arcmap</keyword></searchKeys></dataIdInfo><distInfo><distributor><distorFormat><formatName>ArcToolbox Toolbox</formatName></distorFormat></distributor></distInfo><mdHrLv><ScopeCd value="005"></ScopeCd></mdHrLv></metadata>
